beyondview/Maths.py
beyondview/__init__.py
beyondview/test.py
beyondview-0.1.1.dist-info/LICENSE
beyondview-0.1.1.dist-info/METADATA
beyondview-0.1.1.dist-info/WHEEL
beyondview-0.1.1.dist-info/top_level.txt
beyondview-0.1.1.dist-info/RECORD
